paul_tools/I18n.py
paul_tools/JsonEditor.py
paul_tools/Roll.py
paul_tools/Tools.py
paul_tools/__init__.py
paul_tools/good_list.py
paul_tools/py.typed
paul_tools/Decorator/__init__.py
paul_tools/Decorator/debug.py
paul_tools/Decorator/getTime.py
paul_tools/Decorator/noPrint.py
paul_tools/Decorator/retry.py
paul_tools-1.0.7.dist-info/licenses/LICENSE.txt
paul_tools-1.0.7.dist-info/METADATA
paul_tools-1.0.7.dist-info/WHEEL
paul_tools-1.0.7.dist-info/top_level.txt
paul_tools-1.0.7.dist-info/RECORD
