Metadata-Version: 2.4
Name: paul-tools
Version: 1.0.7
Summary: 一個簡單的lib
Author-email: Paul-16098 <pl816098@gmail.com>
License: MIT License
Project-URL: source, https://github.com/Paul-16098/paul_tools
Requires-Python: >=3.13
License-File: LICENSE.txt
Requires-Dist: loguru
Requires-Dist: colorama
Dynamic: license-file
